latentsync/data/syncnet_dataset.py
latentsync/data/unet_dataset.py
latentsync/models/attention.py
latentsync/models/motion_module.py
latentsync/models/resnet.py
latentsync/models/stable_syncnet.py
latentsync/models/unet.py
latentsync/models/unet_blocks.py
latentsync/models/utils.py
latentsync/models/wav2lip_syncnet.py
latentsync/pipelines/lipsync_pipeline.py
latentsync/trepa/loss.py
latentsync/trepa/third_party/__init__.py
latentsync/trepa/third_party/VideoMAEv2/__init__.py
latentsync/trepa/third_party/VideoMAEv2/utils.py
latentsync/trepa/third_party/VideoMAEv2/videomaev2_finetune.py
latentsync/trepa/third_party/VideoMAEv2/videomaev2_pretrain.py
latentsync/trepa/utils/__init__.py
latentsync/trepa/utils/data_utils.py
latentsync/trepa/utils/metric_utils.py
latentsync/utils/affine_transform.py
latentsync/utils/audio.py
latentsync/utils/av_reader.py
latentsync/utils/image_processor.py
latentsync/utils/util.py
latentsync/whisper/audio2feature.py
latentsync/whisper/whisper/__init__.py
latentsync/whisper/whisper/__main__.py
latentsync/whisper/whisper/audio.py
latentsync/whisper/whisper/decoding.py
latentsync/whisper/whisper/model.py
latentsync/whisper/whisper/tokenizer.py
latentsync/whisper/whisper/transcribe.py
latentsync/whisper/whisper/utils.py
latentsync/whisper/whisper/normalizers/__init__.py
latentsync/whisper/whisper/normalizers/basic.py
latentsync/whisper/whisper/normalizers/english.py
pylatentsync-1.0.0.dist-info/LICENSE
pylatentsync-1.0.0.dist-info/METADATA
pylatentsync-1.0.0.dist-info/WHEEL
pylatentsync-1.0.0.dist-info/top_level.txt
pylatentsync-1.0.0.dist-info/RECORD
