Metadata-Version: 2.1
Name: pylatentsync
Version: 1.0.0
Summary: A python package for LatentSync
Author-email: Long Do <dothanhlongtld@gmail.com>
License: MIT
Project-URL: Homepage, https://github.com/dothanhlongtld/pylatentsync
Project-URL: Bug Tracker, https://github.com/dothanhlongtld/pylatentsync/issues
Keywords: latentsync
Classifier: Programming Language :: Python :: 3
Classifier: License :: OSI Approved :: MIT License
Classifier: Operating System :: OS Independent
Requires-Python: >=3.10
License-File: LICENSE
Requires-Dist: diffusers==0.32.2
Requires-Dist: transformers==4.48.0
Requires-Dist: huggingface-hub==0.25.2
Requires-Dist: decord==0.6.0
Requires-Dist: accelerate==0.26.1
Requires-Dist: einops==0.7.0
Requires-Dist: omegaconf==2.3.0
Requires-Dist: opencv-python==4.9.0.80
Requires-Dist: mediapipe==0.10.11
Requires-Dist: python_speech_features==0.6
Requires-Dist: librosa==0.10.1
Requires-Dist: scenedetect==0.6.1
Requires-Dist: ffmpeg-python==0.2.0
Requires-Dist: lpips==0.1.4
Requires-Dist: face-alignment==1.4.1
Requires-Dist: gradio==5.12.0
Requires-Dist: numpy==1.26.4
